promptrix/AssistantMessage.py
promptrix/ConversationHistory.py
promptrix/FunctionRegistry.py
promptrix/GPT3Tokenizer.py
promptrix/GroupSection.py
promptrix/LayoutEngine.py
promptrix/Prompt.py
promptrix/PromptSectionBase.py
promptrix/SystemMessage.py
promptrix/TemplateSection.py
promptrix/TextSection.py
promptrix/UserMessage.py
promptrix/Utilities.py
promptrix/VolatileMemory.py
promptrix/__init__.py
promptrix/promptrixTypes.py
promptrix-0.3.1.dist-info/LICENSE
promptrix-0.3.1.dist-info/METADATA
promptrix-0.3.1.dist-info/WHEEL
promptrix-0.3.1.dist-info/top_level.txt
promptrix-0.3.1.dist-info/RECORD
