Metadata-Version: 2.1
Name: promptrix
Version: 0.3.1
Summary: Promptrix. A prompt layout manager for LLMs
Author-email: Steven Ickman <author@example.com>, Bruce DAmbrosio <bruce.dambrosio@gmail.com>
Project-URL: Homepage, https://tuuyi.io/promptrix
Project-URL: Bug Tracker, https://github.com/Stevenic/promptrix-py/issues
Classifier: Programming Language :: Python :: 3
Classifier: License :: OSI Approved :: MIT License
Classifier: Operating System :: OS Independent
Requires-Python: >=3.8
License-File: LICENSE
Requires-Dist: requests
Requires-Dist: tiktoken
Requires-Dist: pyyaml
Requires-Dist: importlib-metadata ; python_version < "3.9"
